django_parallel_test.py
django_parallel_test-0.1.0.dist-info/LICENSE
django_parallel_test-0.1.0.dist-info/WHEEL
django_parallel_test-0.1.0.dist-info/METADATA
django_parallel_test-0.1.0.dist-info/RECORD
