Metadata-Version: 2.1
Name: django-parallel-test
Version: 0.1.0
Summary: Django test runner to run a test suite across different machines.
License: MIT
Author: Sid Mitra
Author-email: django-parallel-test@sidmitra.com
Requires-Python: >=3.6.1
Classifier: License :: OSI Approved :: MIT License
Classifier: Programming Language :: Python :: 3
Classifier: Programming Language :: Python :: 3.7
Classifier: Programming Language :: Python :: 3.8
Classifier: Programming Language :: Python :: 3.9
Requires-Dist: Django (>=2.2)
